{
  "drive_roots": {
    "hedge_fund_letters": {
      "folder_id": "0AFpaOm4iTLqjUk9PVA",
      "label": "Single Stock Research PDF Store",
      "source_types": [
        "superinvestor_letter"
      ]
    },
    "general_pdfs": {
      "folder_id": "0AFpaOm4iTLqjUk9PVA",
      "label": "Single Stock Research PDF Store",
      "source_types": [
        "third_party",
        "company_document",
        "research",
        "dropbox_ingestion",
        "sumzero_research",
        "activist_long",
        "activist_short",
        "activist_report",
        "pdf"
      ]
    }
  },
  "default_drive_root": "general_pdfs",
  "drive_intake": {
    "folder_id": "1OBaWt7SF-OME8hmXkl7tzdFLAfjBrp_C",
    "folder_url": "https://drive.google.com/drive/folders/1OBaWt7SF-OME8hmXkl7tzdFLAfjBrp_C",
    "label": "Manual PDF intake (Admin/Intake)",
    "primary_layout": "Admin/Intake/{VIC,Research,Company,Activist/Long,Activist/Short}/{TICKER}.pdf",
    "accepted_layouts": [
      "Admin/Intake/{VIC,Research,Company}/{TICKER}.pdf",
      "Admin/Intake/{VIC,Research,Company}/{TICKER}/*.pdf",
      "Admin/Intake/Activist/Long/{TICKER}/*.pdf",
      "Admin/Intake/Activist/Short/{TICKER}/*.pdf",
      "{VIC,Research,Company}/{TICKER}.pdf",
      "{VIC,Research,Company}/{TICKER}/*.pdf",
      "Admin/{VIC,Research,Company}/{TICKER}.pdf",
      "Admin/{VIC,Research,Company}/{TICKER}/*.pdf",
      "Admin/Activist/Long/{TICKER}/*.pdf",
      "Admin/Activist/Short/{TICKER}/*.pdf"
    ],
    "notes": "Folder id points at Admin/Intake on the Shared Drive. Drop VIC PDFs in the VIC child (or as VIC/{TICKER}.pdf). Do not point this at the VIC child itself or ensure-folders nests Admin/VIC inside VIC."
  },
  "service_account_email": "pdf-store-uploader@single-stock-pdf-store.iam.gserviceaccount.com",
  "folder_strategy": "mirror_source_path",
  "access_model": "shared_drive_permissions",
  "notes": "All PDFs route into one Shared Drive. Hedge fund letters and general PDFs remain separate logical roots only so the registry can organize source types before placing documents into user-facing folders such as Letters and Single Stocks."
}
