{
  "schema_version": "3.0",
  "ticker": "PLWN",
  "as_of": "2026-07-24",
  "status": "partial",
  "error": "Vendor events are discovery evidence; primary-source completeness has not been established.",
  "price_source": "yahoo:PLWN",
  "currency": "USD",
  "return_currency": "USD",
  "fx_basis": "listing_currency_nominal",
  "history_start": "2011-04-13",
  "history_end": "2026-07-23",
  "price_points": 3841,
  "price_interval": "1d",
  "history_basis": "earliest_available_vendor_trading_history",
  "chart_scale": "logarithmic",
  "chart_y_axis": "cumulative_return_pct",
  "chart_series": [
    "total_return",
    "price_only"
  ],
  "return_contract": "split-adjusted close excluding dividends; event amounts normalized for later splits; cash reinvested at ex-date close; pre-tax nominal",
  "coverage": {
    "status": "vendor_only",
    "start": null,
    "end": null,
    "note": "Vendor events are discovery evidence; primary-source completeness has not been established.",
    "ledger_path": null
  },
  "event_count": 17,
  "event_counts": {
    "regular_dividend": 17
  },
  "cash_distributions_on_initial_share_path": 411.4267,
  "distribution_contribution_by_type": {
    "regular_dividend": 411.426684
  },
  "cumulative_distributions_per_share": 411.4267,
  "start_price": 235.0,
  "end_price": 575.0,
  "price_index_end": 244.68,
  "total_return_index_end": 465.94,
  "cumulative_price_return_pct": 144.68,
  "cumulative_total_return_pct": 365.94,
  "price_only_annualized_pct": 6.03,
  "total_return_annualized_pct": 10.6,
  "market_cap_m": 1989.5,
  "shares_outstanding": 3460000,
  "price_for_market_cap": 575.0,
  "chart": "PLWN/research/charts/total_return_2026-07-24.svg"
}
