{
  "events": [
    {
      "event": "rebalance",
      "policy": "ira_marvin",
      "regime": "calm",
      "turnover_pct": 1.65,
      "champion_sharpe": -4.632,
      "population_size": 8,
      "ts": "2026-06-07T01:18:15Z"
    },
    {
      "event": "rebalance",
      "policy": "ira_marvin",
      "regime": "calm",
      "turnover_pct": 0.01,
      "champion_sharpe": -4.027,
      "population_size": 8,
      "ts": "2026-06-07T01:18:16Z"
    },
    {
      "event": "rebalance",
      "policy": "ira_marvin",
      "regime": "calm",
      "turnover_pct": 1.65,
      "champion_sharpe": -4.632,
      "population_size": 8,
      "ts": "2026-06-07T03:52:03Z"
    },
    {
      "event": "rebalance",
      "policy": "ira_marvin",
      "regime": "calm",
      "turnover_pct": 0.01,
      "champion_sharpe": -4.027,
      "population_size": 8,
      "ts": "2026-06-07T03:52:03Z"
    },
    {
      "event": "rebalance",
      "policy": "ira_marvin",
      "regime": "calm",
      "turnover_pct": 1.65,
      "champion_sharpe": -4.632,
      "population_size": 8,
      "ts": "2026-06-07T04:31:51Z"
    },
    {
      "event": "rebalance",
      "policy": "ira_marvin",
      "regime": "calm",
      "turnover_pct": 0.01,
      "champion_sharpe": -4.027,
      "population_size": 8,
      "ts": "2026-06-07T04:31:52Z"
    },
    {
      "event": "rebalance",
      "policy": "ira_marvin",
      "regime": "calm",
      "turnover_pct": 1.65,
      "champion_sharpe": -4.632,
      "population_size": 8,
      "ts": "2026-06-07T17:22:41Z"
    },
    {
      "event": "rebalance",
      "policy": "ira_marvin",
      "regime": "calm",
      "turnover_pct": 0.01,
      "champion_sharpe": -4.027,
      "population_size": 8,
      "ts": "2026-06-07T17:22:41Z"
    },
    {
      "event": "rebalance",
      "policy": "ira_marvin",
      "regime": "calm",
      "turnover_pct": 1.65,
      "champion_sharpe": -4.632,
      "population_size": 8,
      "ts": "2026-06-07T21:43:57Z"
    },
    {
      "event": "rebalance",
      "policy": "ira_marvin",
      "regime": "calm",
      "turnover_pct": 0.01,
      "champion_sharpe": -4.027,
      "population_size": 8,
      "ts": "2026-06-07T21:43:57Z"
    },
    {
      "event": "rebalance",
      "policy": "ira_marvin",
      "regime": "calm",
      "turnover_pct": 1.65,
      "champion_sharpe": -4.632,
      "population_size": 8,
      "ts": "2026-06-08T05:14:51Z"
    },
    {
      "event": "rebalance",
      "policy": "ira_marvin",
      "regime": "calm",
      "turnover_pct": 0.01,
      "champion_sharpe": -4.027,
      "population_size": 8,
      "ts": "2026-06-08T05:14:51Z"
    },
    {
      "event": "rebalance",
      "policy": "ira_marvin",
      "regime": "calm",
      "turnover_pct": 1.65,
      "champion_sharpe": -4.632,
      "population_size": 8,
      "ts": "2026-06-08T16:05:39Z"
    },
    {
      "event": "rebalance",
      "policy": "ira_marvin",
      "regime": "calm",
      "turnover_pct": 0.01,
      "champion_sharpe": -4.027,
      "population_size": 8,
      "ts": "2026-06-08T16:05:40Z"
    },
    {
      "event": "rebalance",
      "policy": "ira_marvin",
      "regime": "calm",
      "turnover_pct": 1.65,
      "champion_sharpe": -4.632,
      "population_size": 8,
      "ts": "2026-06-08T22:38:06Z"
    },
    {
      "event": "rebalance",
      "policy": "ira_marvin",
      "regime": "calm",
      "turnover_pct": 0.01,
      "champion_sharpe": -4.027,
      "population_size": 8,
      "ts": "2026-06-08T22:38:06Z"
    },
    {
      "event": "rebalance",
      "policy": "ira_marvin",
      "regime": "calm",
      "turnover_pct": 1.65,
      "champion_sharpe": -4.632,
      "population_size": 8,
      "ts": "2026-06-10T02:59:48Z"
    },
    {
      "event": "rebalance",
      "policy": "ira_marvin",
      "regime": "calm",
      "turnover_pct": 0.01,
      "champion_sharpe": -4.027,
      "population_size": 8,
      "ts": "2026-06-10T02:59:48Z"
    },
    {
      "event": "rebalance",
      "policy": "ira_marvin",
      "regime": "calm",
      "turnover_pct": 1.65,
      "champion_sharpe": -4.632,
      "population_size": 8,
      "ts": "2026-06-10T16:58:23Z"
    },
    {
      "event": "rebalance",
      "policy": "ira_marvin",
      "regime": "calm",
      "turnover_pct": 0.01,
      "champion_sharpe": -4.027,
      "population_size": 8,
      "ts": "2026-06-10T16:58:23Z"
    }
  ]
}
