{
  "ticker": "CBOE",
  "scan_date": "2026-07-02",
  "source_count": 8,
  "approved_count": 0,
  "pending_count": 1,
  "context_count": 7,
  "sources": [
    {
      "source_id": "vic",
      "title": "VIC PDF intake - CBOE - CBOE VIC PDF",
      "path": "CBOE/third-party-analyses/vic/vic_pdf_2026-06-18_cboe-vic-pdf_f6405ff2d2.pdf",
      "status": "pending",
      "use": "VIC local single-page intake; human approval required"
    },
    {
      "source_id": "activist_short",
      "title": "Block on Bloomberg Markets Discussing Latest Short, Burford Capital",
      "path": "CBOE/third-party-analyses/activist_reports/short/muddy_waters_2019-01-01_block-bloomberg-markets-latest-short-bur.html",
      "status": "context",
      "use": "activist/short \u2014 publisher_site"
    },
    {
      "source_id": "activist_short",
      "title": "Block on Bloomberg Markets Discussing Latest Short, Manulife Financial Corp.",
      "path": "CBOE/third-party-analyses/activist_reports/short/muddy_waters_2018-01-01_block-on-bloomberg-markets-discussing-la.html",
      "status": "context",
      "use": "activist/short \u2014 publisher_site"
    },
    {
      "source_id": "activist_short",
      "title": "Block on Bloomberg Markets Discussing Latest Short, China Internet Financial Services",
      "path": "CBOE/third-party-analyses/activist_reports/short/muddy_waters_2017-01-01_block-on-bloomberg-markets-china-interne.html",
      "status": "context",
      "use": "activist/short \u2014 publisher_site"
    },
    {
      "source_id": "activist_short",
      "title": "Block on Bloomberg Markets Discussing Latest Short, OSI Systems",
      "path": "CBOE/third-party-analyses/activist_reports/short/muddy_waters_2017-01-01_block-bloomberg-markets-discussing-lates.html",
      "status": "context",
      "use": "activist/short \u2014 publisher_site"
    },
    {
      "source_id": "activist_short",
      "title": "Block on Bloomberg Markets Discussing Noble Group",
      "path": "CBOE/third-party-analyses/activist_reports/short/muddy_waters_2017-01-01_block-on-bloomberg-markets-noble.html",
      "status": "context",
      "use": "activist/short \u2014 publisher_site"
    },
    {
      "source_id": "activist_short",
      "title": "Sep 5, 2018",
      "path": "CBOE/third-party-analyses/activist_reports/short/spruce_point_2018-01-01_weis-markets-inc.html",
      "status": "context",
      "use": "activist/short \u2014 publisher_site"
    },
    {
      "source_id": "activist_short",
      "title": "viceroy",
      "path": "CBOE/third-party-analyses/activist_reports/short/viceroy_2026-01-01_osc-and-ciro.html",
      "status": "context",
      "use": "activist/short \u2014 local"
    }
  ],
  "hk_indexed": false
}
